winrt/_winrt_windows_storage.cp313-win32.pyd
winrt/_winrt_windows_storage.pyi
winrt/windows/storage/__init__.py
winrt/windows/storage/py.typed
winrt_windows_storage-3.2.0.dist-info/METADATA
winrt_windows_storage-3.2.0.dist-info/WHEEL
winrt_windows_storage-3.2.0.dist-info/top_level.txt
winrt_windows_storage-3.2.0.dist-info/RECORD
